[
    {
        "key": "dbln",
        "value": "%7B%2261560525105663%22%3A%22VgoynesL%22%2C%2261553957082778%22%3A%223Tw94FjT%22%2C%22100092287005205%22%3A%22SLyhV6wA%22%7D",
        "domain": "facebook.com",
        "path": "/login/device-based/",
        "hostOnly": false,
        "creation": "2024-12-22T07:46:59.920Z",
        "lastAccessed": "2024-12-22T07:46:59.920Z"
    },
    {
        "key": "sb",
        "value": "jXD_ZiHt07O5Txoko8K7buiG",
        "domain": "facebook.com",
        "path": "/",
        "hostOnly": false,
        "creation": "2024-12-22T07:46:59.920Z",
        "lastAccessed": "2024-12-22T07:46:59.920Z"
    },
    {
        "key": "datr",
        "value": "jXD_ZkUCLw2Ye3107yVJ-CU-",
        "domain": "facebook.com",
        "path": "/",
        "hostOnly": false,
        "creation": "2024-12-22T07:46:59.920Z",
        "lastAccessed": "2024-12-22T07:46:59.920Z"
    },
    {
        "key": "ps_l",
        "value": "1",
        "domain": "facebook.com",
        "path": "/",
        "hostOnly": false,
        "creation": "2024-12-22T07:46:59.920Z",
        "lastAccessed": "2024-12-22T07:46:59.920Z"
    },
    {
        "key": "ps_n",
        "value": "1",
        "domain": "facebook.com",
        "path": "/",
        "hostOnly": false,
        "creation": "2024-12-22T07:46:59.920Z",
        "lastAccessed": "2024-12-22T07:46:59.920Z"
    },
    {
        "key": "vpd",
        "value": "v1%3B1275x668x1.618749976158142",
        "domain": "facebook.com",
        "path": "/",
        "hostOnly": false,
        "creation": "2024-12-22T07:46:59.920Z",
        "lastAccessed": "2024-12-22T07:46:59.920Z"
    },
    {
        "key": "dpr",
        "value": "1.618749976158142",
        "domain": "facebook.com",
        "path": "/",
        "hostOnly": false,
        "creation": "2024-12-22T07:46:59.920Z",
        "lastAccessed": "2024-12-22T07:46:59.921Z"
    },
    {
        "key": "wd",
        "value": "668x1275",
        "domain": "facebook.com",
        "path": "/",
        "hostOnly": false,
        "creation": "2024-12-22T07:46:59.921Z",
        "lastAccessed": "2024-12-22T07:46:59.921Z"
    },
    {
        "key": "c_user",
        "value": "100092287005205",
        "domain": "facebook.com",
        "path": "/",
        "hostOnly": false,
        "creation": "2024-12-22T07:46:59.921Z",
        "lastAccessed": "2024-12-22T07:46:59.921Z"
    },
    {
        "key": "xs",
        "value": "19%3AUgZcwh8ddmp2bw%3A2%3A1734598475%3A-1%3A6279",
        "domain": "facebook.com",
        "path": "/",
        "hostOnly": false,
        "creation": "2024-12-22T07:46:59.921Z",
        "lastAccessed": "2024-12-22T07:46:59.921Z"
    },
    {
        "key": "i_user",
        "value": "61565589964403",
        "domain": "facebook.com",
        "path": "/",
        "hostOnly": false,
        "creation": "2024-12-22T07:46:59.921Z",
        "lastAccessed": "2024-12-22T07:46:59.921Z"
    },
    {
        "key": "locale",
        "value": "en_US",
        "domain": "facebook.com",
        "path": "/",
        "hostOnly": false,
        "creation": "2024-12-22T07:46:59.921Z",
        "lastAccessed": "2024-12-22T07:46:59.921Z"
    },
    {
        "key": "fbl_st",
        "value": "100421569%3BT%3A28914226",
        "domain": "facebook.com",
        "path": "/",
        "hostOnly": false,
        "creation": "2024-12-22T07:46:59.921Z",
        "lastAccessed": "2024-12-22T07:46:59.921Z"
    },
    {
        "key": "wl_cbv",
        "value": "v2%3Bclient_version%3A2701%3Btimestamp%3A1734853587",
        "domain": "facebook.com",
        "path": "/",
        "hostOnly": false,
        "creation": "2024-12-22T07:46:59.921Z",
        "lastAccessed": "2024-12-22T07:46:59.921Z"
    },
    {
        "key": "fr",
        "value": "1AT2FCyWYewu9gria.AWXK2SOOdPHdQn7BXIrNz4u3ugg.BnXp_7..AAA.0.0.BnZ8Pj.AWU-VoHg5Dw",
        "domain": "facebook.com",
        "path": "/",
        "hostOnly": false,
        "creation": "2024-12-22T07:46:59.921Z",
        "lastAccessed": "2024-12-22T07:46:59.921Z"
    }
